fintecture/__init__.py
fintecture/api_requestor.py
fintecture/constants.py
fintecture/crypto.py
fintecture/environments.py
fintecture/error.py
fintecture/fintecture_object.py
fintecture/fintecture_response.py
fintecture/http_client.py
fintecture/multipart_data_generator.py
fintecture/oauth.py
fintecture/object_classes.py
fintecture/request_metrics.py
fintecture/six.py
fintecture/util.py
fintecture/version.py
fintecture/webhook.py
fintecture/api_resources/__init__.py
fintecture/api_resources/account.py
fintecture/api_resources/account_holder.py
fintecture/api_resources/ais.py
fintecture/api_resources/application.py
fintecture/api_resources/capability.py
fintecture/api_resources/charge.py
fintecture/api_resources/customer.py
fintecture/api_resources/ephemeral_key.py
fintecture/api_resources/error_object.py
fintecture/api_resources/list_object.py
fintecture/api_resources/payment.py
fintecture/api_resources/payout.py
fintecture/api_resources/pis.py
fintecture/api_resources/provider.py
fintecture/api_resources/refund.py
fintecture/api_resources/search_result_object.py
fintecture/api_resources/test_account.py
fintecture/api_resources/token.py
fintecture/api_resources/usage_record.py
fintecture/api_resources/usage_record_summary.py
fintecture/api_resources/webhook_endpoint.py
fintecture/api_resources/abstract/__init__.py
fintecture/api_resources/abstract/api_resource.py
fintecture/api_resources/abstract/createable_api_resource.py
fintecture/api_resources/abstract/custom_method.py
fintecture/api_resources/abstract/deletable_api_resource.py
fintecture/api_resources/abstract/listable_api_resource.py
fintecture/api_resources/abstract/nested_resource_class_methods.py
fintecture/api_resources/abstract/searchable_api_resource.py
fintecture/api_resources/abstract/singleton_api_resource.py
fintecture/api_resources/abstract/test_helpers.py
fintecture/api_resources/abstract/updateable_api_resource.py
fintecture/api_resources/abstract/verify_mixin.py
fintecture-1.3.1.dist-info/LICENSE
fintecture-1.3.1.dist-info/METADATA
fintecture-1.3.1.dist-info/WHEEL
fintecture-1.3.1.dist-info/top_level.txt
fintecture-1.3.1.dist-info/RECORD
