Metadata-Version: 2.1
Name: fintecture
Version: 1.3.1
Summary: Python bindings for the Fintecture API
Home-page: https://github.com/Fintecture/fintecture-sdk-python
Author: Fintecture
Author-email: contact@fintecture.com
License: The MIT License
Project-URL: Bug Tracker, https://github.com/Fintecture/fintecture-sdk-python/issues
Project-URL: Changes, https://github.com/Fintecture/fintecture-sdk-python/blob/master/CHANGELOG.md
Project-URL: Documentation, https://fintecture.com/docs/api/?lang=python
Project-URL: Source Code, https://github.com/Fintecture/fintecture-sdk-python
Keywords: fintecture api payments
Classifier: Programming Language :: Python :: 3
Classifier: License :: OSI Approved :: MIT License
Classifier: Operating System :: OS Independent
Requires-Python: >=2.7, !=3.0.*, !=3.1.*, !=3.2.*, !=3.3.*
License-File: LICENSE
Requires-Dist: cryptography (~=37.0.4)
Requires-Dist: requests[security] (>=2.20) ; python_version < "3.0"
Requires-Dist: requests (>=2.20) ; python_version >= "3.0"
